netbox_ip_monitor/__init__.py
netbox_ip_monitor/template_content.py
netbox_ip_monitor/templates/netbox_ip_monitor/ip_monitor.html
netbox_ip_monitor-0.1.3.dist-info/licenses/LICENSE
netbox_ip_monitor-0.1.3.dist-info/METADATA
netbox_ip_monitor-0.1.3.dist-info/WHEEL
netbox_ip_monitor-0.1.3.dist-info/top_level.txt
netbox_ip_monitor-0.1.3.dist-info/RECORD
