Metadata-Version: 2.4
Name: netbox_ip_monitor
Version: 0.1.3
Summary: Visual representation of IP addresses
Home-page: https://github.com/Future998/netbox-ip-monitor
Author: Alexander Burmatov
Author-email: burmatov202002@gmail.com
License: Apache 2.0
Keywords: netbox ip monitor plugin
License-File: LICENSE
Dynamic: author
Dynamic: author-email
Dynamic: description
Dynamic: description-content-type
Dynamic: home-page
Dynamic: keywords
Dynamic: license
Dynamic: license-file
Dynamic: summary
